goofish_api/__init__.py
goofish_api/__version__.py
goofish_api/api/__init__.py
goofish_api/api/base.py
goofish_api/api/good.py
goofish_api/api/order.py
goofish_api/api/other.py
goofish_api/api/user.py
goofish_api/utils/__init__.py
goofish_api/utils/api_response.py
goofish_api/utils/base_client.py
goofish_api/utils/constants.py
goofish_api/utils/helpers.py
goofish_api-0.0.6.dist-info/LICENSE
goofish_api-0.0.6.dist-info/METADATA
goofish_api-0.0.6.dist-info/WHEEL
goofish_api-0.0.6.dist-info/top_level.txt
goofish_api-0.0.6.dist-info/RECORD
