Metadata-Version: 2.1
Name: goofish_api
Version: 0.0.6
Summary: Python wrapper for the goofish API
Home-page: https://github.com/xie7654/goofish_api
Author: XIE JUN
Author-email: xie765462425@gmail.com
License: MIT
License-File: LICENSE
